xlsxreader/__init__.py
xlsxreader/xlsxreader.py
xlsxreader-0.1.12.dist-info/LICENSE
xlsxreader-0.1.12.dist-info/METADATA
xlsxreader-0.1.12.dist-info/WHEEL
xlsxreader-0.1.12.dist-info/top_level.txt
xlsxreader-0.1.12.dist-info/RECORD
